aiocache/__init__.py
aiocache/_version.py
aiocache/base.py
aiocache/decorators.py
aiocache/exceptions.py
aiocache/factory.py
aiocache/lock.py
aiocache/plugins.py
aiocache/backends/__init__.py
aiocache/backends/memcached.py
aiocache/backends/memory.py
aiocache/backends/redis.py
aiocache/serializers/__init__.py
aiocache/serializers/serializers.py
seoservice2020_aiocache-1.0.0.dist-info/LICENSE
seoservice2020_aiocache-1.0.0.dist-info/METADATA
seoservice2020_aiocache-1.0.0.dist-info/WHEEL
seoservice2020_aiocache-1.0.0.dist-info/top_level.txt
seoservice2020_aiocache-1.0.0.dist-info/RECORD
