Metadata-Version: 2.1
Name: seoservice2020-aiocache
Version: 1.0.0
Summary: multi backend asyncio cache
Home-page: https://github.com/SEOService2020/aiocache
Author: Manuel Miranda
Author-email: manu.mirandad@gmail.com
License: UNKNOWN
Platform: UNKNOWN
Classifier: Programming Language :: Python
Classifier: Programming Language :: Python :: 3.6
Classifier: Programming Language :: Python :: 3.7
Classifier: Programming Language :: Python :: 3.8
Classifier: Programming Language :: Python :: 3.9
Classifier: Framework :: AsyncIO
License-File: LICENSE
Provides-Extra: dev
Requires-Dist: asynctest (>=0.11.0) ; extra == 'dev'
Requires-Dist: codecov ; extra == 'dev'
Requires-Dist: coverage ; extra == 'dev'
Requires-Dist: flake8 ; extra == 'dev'
Requires-Dist: ipdb ; extra == 'dev'
Requires-Dist: marshmallow (>=3) ; extra == 'dev'
Requires-Dist: pystache ; extra == 'dev'
Requires-Dist: pytest ; extra == 'dev'
Requires-Dist: pytest-asyncio ; extra == 'dev'
Requires-Dist: pytest-mock ; extra == 'dev'
Requires-Dist: sphinx ; extra == 'dev'
Requires-Dist: sphinx-autobuild ; extra == 'dev'
Requires-Dist: sphinx-rtd-theme ; extra == 'dev'
Requires-Dist: black ; (python_version >= "3.6") and extra == 'dev'
Provides-Extra: memcached
Requires-Dist: aiomcache (>=0.5.2) ; extra == 'memcached'
Provides-Extra: msgpack
Requires-Dist: msgpack (>=0.5.5) ; extra == 'msgpack'
Provides-Extra: redis
Requires-Dist: aioredis (>=0.3.3) ; (python_version<"3.7") and extra == 'redis'
Requires-Dist: aioredis (>=1.0.0) ; (python_version>="3.7" and python_version<"3.8") and extra == 'redis'
Requires-Dist: aioredis (>=1.3.0) ; (python_version>="3.8") and extra == 'redis'
